LICENSE
MANIFEST.in
README.rst
RELEASE-VERSION
setup.py
gitpy_versioning/.git
gitpy_versioning/.gitignore
gitpy_versioning/README.md
gitpy_versioning/__init__.py
gitpy_versioning/__init__.pyc
gitpy_versioning/test_gitpy_versioning.py
steelscript/__init__.py
steelscript.stock.egg-info/PKG-INFO
steelscript.stock.egg-info/SOURCES.txt
steelscript.stock.egg-info/dependency_links.txt
steelscript.stock.egg-info/entry_points.txt
steelscript.stock.egg-info/namespace_packages.txt
steelscript.stock.egg-info/not-zip-safe
steelscript.stock.egg-info/requires.txt
steelscript.stock.egg-info/top_level.txt
steelscript/stock/__init__.py
steelscript/stock/appfwk/__init__.py
steelscript/stock/appfwk/admin.py
steelscript/stock/appfwk/models.py
steelscript/stock/appfwk/plugin.py
steelscript/stock/appfwk/datasources/__init__.py
steelscript/stock/appfwk/datasources/stock_source.py
steelscript/stock/appfwk/libs/__init__.py
steelscript/stock/appfwk/reports/__init__.py
steelscript/stock/appfwk/reports/multi_stock_report.py
steelscript/stock/appfwk/reports/stock_report.py
steelscript/stock/commands/__init__.py
steelscript/stock/commands/subcommand.py
steelscript/stock/core/__init__.py
steelscript/stock/core/app.py